syringe_pump/__init__.py
syringe_pump/_version.py
syringe_pump/device.py
syringe_pump/device_client.py
syringe_pump/device_gui.py
syringe_pump/device_io.py
syringe_pump/driver.py
syringe_pump/mock_driver.py
syringe_pump/tests/__init__.py
syringe_pump/tests/conftest.py
syringe_pump/tests/test_examples.py
syringe_pump-0.0.13.dist-info/AUTHORS.rst
syringe_pump-0.0.13.dist-info/LICENSE
syringe_pump-0.0.13.dist-info/METADATA
syringe_pump-0.0.13.dist-info/WHEEL
syringe_pump-0.0.13.dist-info/entry_points.txt
syringe_pump-0.0.13.dist-info/top_level.txt
syringe_pump-0.0.13.dist-info/RECORD
