Metadata-Version: 2.1
Name: syringe-pump
Version: 0.0.13
Summary: Cavro Centris Syringe Pump
Home-page: https://github.com/vstadnytskyi/syringe-pump
Author: Valentyn Stadnytskyi
Author-email: v.stadnytskyi@gmail.com
License: BSD (3-clause)
Platform: UNKNOWN
Classifier: Development Status :: 2 - Pre-Alpha
Classifier: Natural Language :: English
Classifier: Programming Language :: Python :: 3
Requires-Python: >=3.6
Requires-Dist: circular-buffer-numpy
Requires-Dist: numpy
Requires-Dist: ubcs-auxiliary
Requires-Dist: caproto
Requires-Dist: pyserial
